postpy2/__init__.py
postpy2/core.py
postpy2/extractors.py
postpy2-0.0.8.dist-info/LICENSE.md
postpy2-0.0.8.dist-info/METADATA
postpy2-0.0.8.dist-info/WHEEL
postpy2-0.0.8.dist-info/top_level.txt
postpy2-0.0.8.dist-info/RECORD
