Metadata-Version: 2.1
Name: postpy2
Version: 0.0.8
Summary: A library to use postman collection V2 in python.
Home-page: https://github.com/matkapi/postpy2
Download-URL: https://codeload.github.com/matkapi/postpy2/zip/master
Author: Martin Kapinos
Author-email: matkapi19@gmail.com
Keywords: postman,rest,api
Classifier: Programming Language :: Python :: 3
Classifier: License :: OSI Approved :: GNU General Public License v3 (GPLv3)
Classifier: Operating System :: OS Independent
Requires-Python: >=3.6
License-File: LICENSE.md
Requires-Dist: requests
Requires-Dist: python-magic
Requires-Dist: mergedeep
